fiuai_sdk_python/__init__.py
fiuai_sdk_python/bank.py
fiuai_sdk_python/client.py
fiuai_sdk_python/company.py
fiuai_sdk_python/config.py
fiuai_sdk_python/const.py
fiuai_sdk_python/context.py
fiuai_sdk_python/datatype.py
fiuai_sdk_python/doctype.py
fiuai_sdk_python/error.py
fiuai_sdk_python/item.py
fiuai_sdk_python/perm.py
fiuai_sdk_python/profile.py
fiuai_sdk_python/resp.py
fiuai_sdk_python/setup.py
fiuai_sdk_python/type.py
fiuai_sdk_python/util.py
fiuai_sdk_python/auth/__init__.py
fiuai_sdk_python/auth/context_mgr.py
fiuai_sdk_python/auth/header.py
fiuai_sdk_python/auth/helper.py
fiuai_sdk_python/auth/type.py
fiuai_sdk_python/examples/fastapi_integration.py
fiuai_sdk_python/http/__init__.py
fiuai_sdk_python/http/client.py
fiuai_sdk_python/pkg/cache/__init__.py
fiuai_sdk_python/pkg/cache/redis_manager.py
fiuai_sdk_python/utils/__init__.py
fiuai_sdk_python/utils/ids.py
fiuai_sdk_python/utils/logger.py
fiuai_sdk_python/utils/text.py
fiuai_sdk_python-0.7.1.dist-info/METADATA
fiuai_sdk_python-0.7.1.dist-info/WHEEL
fiuai_sdk_python-0.7.1.dist-info/licenses/LICENSE
fiuai_sdk_python-0.7.1.dist-info/RECORD
