Metadata-Version: 2.4
Name: fiuai_sdk_python
Version: 0.7.1
Summary: FiuAI Python SDK - 企业级AI服务集成开发工具包
Project-URL: Homepage, https://github.com/fiuai/fiuai-sdk-python
Project-URL: Documentation, https://github.com/fiuai/fiuai-sdk-python#readme
Project-URL: Repository, https://github.com/fiuai/fiuai-sdk-python.git
Project-URL: Issues, https://github.com/fiuai/fiuai-sdk-python/issues
Project-URL: Changelog, https://github.com/fiuai/fiuai-sdk-python/blob/main/CHANGELOG.md
Author-email: liming <lmlala@aliyun.com>
Maintainer-email: liming <lmlala@aliyun.com>
License: MIT
License-File: LICENSE
Keywords: ai,enterprise,fiuai,python,sdk
Classifier: Development Status :: 4 - Beta
Classifier: Intended Audience :: Developers
Classifier: License :: OSI Approved :: MIT License
Classifier: Operating System :: OS Independent
Classifier: Programming Language :: Python :: 3
Classifier: Programming Language :: Python :: 3.12
Classifier: Programming Language :: Python :: 3.13
Classifier: Topic :: Software Development :: Libraries :: Application Frameworks
Classifier: Topic :: Software Development :: Libraries :: Python Modules
Requires-Python: >=3.12
Requires-Dist: fastapi>=0.118.2
Requires-Dist: httpx>=0.28.1
Requires-Dist: langgraph-checkpoint-redis>=0.3.1
Requires-Dist: pydantic>=2.11.7
Requires-Dist: pytest>=8.4.1
Requires-Dist: redis>=7.1.0
Requires-Dist: snowflake-id>=1.0.2
Requires-Dist: tenacity>=9.1.2
